__init__.py
codeowners_lib.py
github_fetch_file.py
gh_codeowners-0.0.2.dist-info/LICENSE
gh_codeowners-0.0.2.dist-info/METADATA
gh_codeowners-0.0.2.dist-info/WHEEL
gh_codeowners-0.0.2.dist-info/top_level.txt
gh_codeowners-0.0.2.dist-info/RECORD
